pyerg.cp37-win_amd64.pyd
pyerg-0.6.1.dist-info/LICENSE
pyerg-0.6.1.dist-info/METADATA
pyerg-0.6.1.dist-info/WHEEL
pyerg-0.6.1.dist-info/top_level.txt
pyerg-0.6.1.dist-info/RECORD
