Metadata-Version: 2.1
Name: pyerg
Version: 0.6.1
Summary: Python C extension to read IPG CarMaker ERG files
Home-page: http://www.henesis.eu
Author: Alessandro Bacchini
Author-email: alessandro.bacchini@henesis.eu
License: MIT
Platform: UNKNOWN
Classifier: Development Status :: 4 - Beta
Classifier: Intended Audience :: Science/Research
Classifier: Topic :: Scientific/Engineering
Classifier: License :: OSI Approved :: MIT License
Classifier: Programming Language :: Python :: 3.7
Classifier: Programming Language :: Python :: 3.8
Classifier: Programming Language :: Python :: 3.9
Requires-Dist: numpy (>=1.14)
